HandyLib/__init__.py
HandyLib/count.py
HandyLib/erase_partition.py
HandyLib/file_operator.py
HandyLib/network.py
HandyLib/read_meta.py
HandyLib-0.0.8.dist-info/LICENSE
HandyLib-0.0.8.dist-info/METADATA
HandyLib-0.0.8.dist-info/WHEEL
HandyLib-0.0.8.dist-info/top_level.txt
HandyLib-0.0.8.dist-info/RECORD
