Metadata-Version: 2.1
Name: HandyLib
Version: 0.0.8
Summary: A Handy Library
Home-page: https://github.com/QY-Y/HandyLib
Author: QY-Y
Author-email: QY-Y@qq.com
License: UNKNOWN
Platform: UNKNOWN
Classifier: Programming Language :: Python :: 3
Classifier: License :: OSI Approved :: MIT License
Classifier: Operating System :: Microsoft :: Windows :: Windows 10
License-File: LICENSE
